fxapom/__init__.py
fxapom/fxapom.py
fxapom/pages/__init__.py
fxapom/pages/base.py
fxapom/pages/sign_in.py
fxapom-1.10.2.dist-info/METADATA
fxapom-1.10.2.dist-info/RECORD
fxapom-1.10.2.dist-info/WHEEL
fxapom-1.10.2.dist-info/top_level.txt
