Metadata-Version: 2.1
Name: fxapom
Version: 1.10.2
Summary: Mozilla Firefox Accounts Page Object Model
Home-page: https://github.com/mozilla/fxapom
Author: Firefox Test Engineering
Author-email: firefox-test-engineering@mozilla.com
License: MPL 2.0
Keywords: mozilla
Platform: UNKNOWN
Classifier: Development Status :: 5 - Production/Stable
Classifier: Intended Audience :: Developers
Classifier: License :: OSI Approved :: Mozilla Public License 2.0 (MPL 2.0)
Classifier: Operating System :: POSIX
Classifier: Operating System :: Microsoft :: Windows
Classifier: Operating System :: MacOS :: MacOS X
Classifier: Topic :: Software Development :: Testing
Classifier: Topic :: Utilities
Classifier: Programming Language :: Python
Classifier: Programming Language :: Python :: 2.6
Classifier: Programming Language :: Python :: 2.7
Classifier: Programming Language :: Python :: 3.6
Requires-Dist: PyFxA
Requires-Dist: PyPOM
